CHANGES.rst
CONTRIBUTORS.rst
DEVELOP.rst
LICENSE.GPL
LICENSE.rst
MANIFEST.in
README.rst
requirements.txt
setup.cfg
setup.py
src/collective/__init__.py
src/collective.linkcheck.egg-info/PKG-INFO
src/collective.linkcheck.egg-info/SOURCES.txt
src/collective.linkcheck.egg-info/dependency_links.txt
src/collective.linkcheck.egg-info/entry_points.txt
src/collective.linkcheck.egg-info/namespace_packages.txt
src/collective.linkcheck.egg-info/not-zip-safe
src/collective.linkcheck.egg-info/requires.txt
src/collective.linkcheck.egg-info/top_level.txt
src/collective/linkcheck/__init__.py
src/collective/linkcheck/browser.py
src/collective/linkcheck/configure.zcml
src/collective/linkcheck/controlpanel.py
src/collective/linkcheck/events.py
src/collective/linkcheck/export.py
src/collective/linkcheck/interfaces.py
src/collective/linkcheck/parse.py
src/collective/linkcheck/processor.py
src/collective/linkcheck/queue.py
src/collective/linkcheck/tool.py
src/collective/linkcheck/traversal.py
src/collective/linkcheck/upgrades.py
src/collective/linkcheck/locales/collective.linkcheck.pot
src/collective/linkcheck/locales/update.sh
src/collective/linkcheck/locales/de/LC_MESSAGES/collective.linkcheck.po
src/collective/linkcheck/locales/en/LC_MESSAGES/collective.linkcheck.po
src/collective/linkcheck/profiles/default/browserlayer.xml
src/collective/linkcheck/profiles/default/controlpanel.xml
src/collective/linkcheck/profiles/default/metadata.xml
src/collective/linkcheck/profiles/default/registry.xml
src/collective/linkcheck/profiles/default/toolset.xml
src/collective/linkcheck/templates/empty.pt
src/collective/linkcheck/templates/report.pt
src/collective/linkcheck/templates/rss.pt
src/collective/linkcheck/templates/stats.pt