Metadata-Version: 1.1
Name: collective.linkcheck
Version: 1.5
Summary: Add-on for Plone that provides link validity checking and reporting.
Home-page: https://pypi.python.org/pypi/collective.linkcheck
Author: Malthe Borch
Author-email: mborch@gmail.com
License: GPL version 2
Keywords: Python Plone
Platform: UNKNOWN
Classifier: Environment :: Web Environment
Classifier: Framework :: Plone
Classifier: Framework :: Plone :: 4.3
Classifier: Framework :: Plone :: 5.0
Classifier: Programming Language :: Python
Classifier: Programming Language :: Python :: 2.7
Classifier: Operating System :: OS Independent
Classifier: License :: OSI Approved :: GNU General Public License v2 (GPLv2)
